citationnet/__init__.py
citationnet/interface.py
citationnet/network.py
citationnet/static/data/Aleksandra_Kaye_W4394718639.json
citationnet/static/data/Jahel_Mielke_W2802046069.json
citationnet/static/data/Johan_Rockström_W3139533848.json
citationnet/static/data/Jürgen_Renn_W4234174590.json
citationnet/static/data/Malte_Vogl_W2083876332.json
citationnet/static/data/Patrick_Roberts_W4390754330.json
citationnet/static/data/William_H._Sewell_W2064403943.json
citationnet/static/data/data_readme.md
citationnet/static/images/logo.png
citationnet/static/images/mpg.png
citationnet/templates/control.html
citationnet/templates/drawnetwork.html
citationnet/templates/index.html
citationnet/templates/startpage.html
citationnet-2.1.0.dist-info/METADATA
citationnet-2.1.0.dist-info/WHEEL
citationnet-2.1.0.dist-info/licenses/AUTHORS.md
citationnet-2.1.0.dist-info/licenses/LICENSE.md
citationnet-2.1.0.dist-info/RECORD
