Metadata-Version: 2.3
Name: citationnet
Version: 2.1.0
Summary: Create a scientific network visualization.
Project-URL: Project Homepage, https://modelsen.gea.mpg.de
Project-URL: Homepage, https://gitlab.gwdg.de/mpigea/dt/citationnet-interface
Project-URL: Issues, https://gitlab.gwdg.de/mpigea/dt/citationnet-interface/-/issues
Author-email: Malte Vogl <vogl@gea.mpg.de>
License-File: AUTHORS.md
License-File: LICENSE.md
Classifier: License :: OSI Approved :: MIT License
Classifier: Operating System :: OS Independent
Classifier: Programming Language :: Python :: 3
Requires-Python: >=3.8
Requires-Dist: fastapi
Requires-Dist: httpx
Requires-Dist: jinja2
Requires-Dist: pandas
Requires-Dist: python-multipart
Requires-Dist: requests
Requires-Dist: tqdm
Requires-Dist: uvicorn
Provides-Extra: dev
Requires-Dist: myst-parser; extra == 'dev'
Requires-Dist: ruff; extra == 'dev'
Requires-Dist: sphinx; extra == 'dev'
Requires-Dist: tox; extra == 'dev'
Requires-Dist: twine; extra == 'dev'
